{"tag":"lexa","tileMap":{"name":"","width":8,"height":8,"tiles":[[12,12,13,13,13,12,12,12],[10,10,12,12,12,13,10,10],[12,10,10,12,12,13,12,10],[12,13,10,21,21,21,10,10],[12,10,13,12,10,10,12,12],[12,10,13,21,13,13,13,13],[12,10,12,21,12,10,21,21],[21,11,12,12,12,10,10,12]],"collision":[[0,0,0,0,0,0,0,0],[0,0,0,0,0,0,0,0],[0,0,0,0,0,0,0,0],[0,0,0,1,1,1,0,0],[0,0,0,0,0,0,0,0],[0,0,0,1,0,0,0,0],[0,0,0,1,0,0,1,1],[1,0,0,0,0,0,0,0]],"zones":[{"id":31,"x":7,"y":7,"type":"win"},{"id":30,"x":1,"y":1,"type":"start"},{"id":52,"x":7,"y":1,"type":"colored","properties":["red"]},{"id":50,"x":6,"y":5,"type":"colored","properties":["green"]},{"id":52,"x":1,"y":3,"type":"colored","properties":["red"]}]},"title":"What","codeLinesNum":16,"allowedInstructions":["MOVE","NONE","GOTO","ROT"]}